{
  "html": {
    "snippets": {
      "rvt-button-group": "<div class=\"rvt-button-group\">\n\t$1\n</div>",
      "rvt-button-group:segmented": "<div class=\"rvt-button-segmented\" role=\"group\" aria-label=\"${1:Button group label}\">\n\t$2\n</div>",
      "rvt-button-group:segmented:fitted": "<div class=\"rvt-button-segmented rvt-button-segmented--fitted\" role=\"group\" aria-label=\"${1:Button group label}\">\n\t$2\n</div>",
      "rvt-checkbox": "<input type=\"checkbox\" name=\"${1:checkbox-name}\" id=\"${2:checkbox-id}\">\n<label for=\"${3:checkbox-id}\" class=\"rvt-m-right-sm\">${4:Checkbox label}</label>",
      "rvt-radio": "<input type=\"radio\" name=\"${1:radio-name}\" id=\"${2:radio-id}\">\n<label for=\"${3:radio-id}\" class=\"rvt-m-right-md\">${4:Radio button label}</label>",
      "rvt-upload": "<div class=\"rvt-file\" data-upload=\"${1:file-input-id}\">\n\t<input type=\"file\" id=\"${2:file-input-id}\" aria-describedby=\"file-description\">\n\t<label for=\"${3:file-input-id}\" class=\"rvt-button\">\n\t\t<span>Upload a file</span>\n\t\t<svg role=\"img\" alt=\"\" xmlns=\"http://www.w3.org/2000/svg\" width=\"16\" height=\"16\" viewBox=\"0 0 16 16\">\n\t\t\t<path fill=\"currentColor\" d=\"M10.41,1H3.5A1.3,1.3,0,0,0,2.2,2.3V13.7A1.3,1.3,0,0,0,3.5,15h9a1.3,1.3,0,0,0,1.3-1.3V4.39ZM11.8,5.21V6H9.25V3h.34ZM4.2,13V3h3V6.75A1.25,1.25,0,0,0,8.5,8h3.3v5Z\"/>\n\t\t</svg>\n\t</label>\n\t<div class=\"rvt-file__preview\" data-file-preview=\"${4:file-input-id}\" id=\"file-description\">\n\t\tNo file selected\n\t</div>\n</div>",
      "rvt-upload:multiple": "<div class=\"rvt-file\" data-upload=\"${1:file-input-id}\">\n\t<input type=\"file\" id=\"${2:file-input-id}\" aria-describedby=\"file-description\" multiple>\n\t<label for=\"${3:file-input-id}\" class=\"rvt-button\">\n\t\t<span>Upload a file</span>\n\t\t<svg role=\"img\" alt=\"\" xmlns=\"http://www.w3.org/2000/svg\" width=\"16\" height=\"16\" viewBox=\"0 0 16 16\">\n\t\t\t<path fill=\"currentColor\" d=\"M10.41,1H3.5A1.3,1.3,0,0,0,2.2,2.3V13.7A1.3,1.3,0,0,0,3.5,15h9a1.3,1.3,0,0,0,1.3-1.3V4.39ZM11.8,5.21V6H9.25V3h.34ZM4.2,13V3h3V6.75A1.25,1.25,0,0,0,8.5,8h3.3v5Z\"/>\n\t\t</svg>\n\t</label>\n\t<div class=\"rvt-file__preview\" data-file-preview=\"${4:file-input-id}\" id=\"file-description\">\n\t\tNo file selected\n\t</div>\n</div>",
      "rvt-alert:info": "<div class=\"rvt-alert rvt-alert--info rvt-m-bottom-md\" role=\"alertdialog\" aria-labelledby=\"information-alert-title\">\n\t<h1 class=\"rvt-alert__title\" id=\"information-alert-title\">$1</h1>\n\t<p class=\"rvt-alert__message\">$2</p>\n\t<button class=\"rvt-alert__dismiss\">\n\t\t<span class=\"v-hide\">Dismiss this alert</span>\n\t\t<svg role=\"img\" alt=\"\" xmlns=\"http://www.w3.org/2000/svg\" width=\"16\" height=\"16\" viewBox=\"0 0 16 16\">\n\t\t\t<path fill=\"currentColor\" d=\"M9.41,8l5.29-5.29a1,1,0,0,0-1.41-1.41L8,6.59,2.71,1.29A1,1,0,0,0,1.29,2.71L6.59,8,1.29,13.29a1,1,0,1,0,1.41,1.41L8,9.41l5.29,5.29a1,1,0,0,0,1.41-1.41Z\"/>\n\t\t</svg>\n\t</button>\n</div>",
      "rvt-alert:success": "<div class=\"rvt-alert rvt-alert--success rvt-m-bottom-md\" role=\"alertdialog\" aria-labelledby=\"success-alert-title\">\n\t<h1 class=\"rvt-alert__title\" id=\"success-alert-title\">$1</h1>\n\t<p class=\"rvt-alert__message\">$2</p>\n\t<button class=\"rvt-alert__dismiss\">\n\t\t<span class=\"v-hide\">Dismiss this alert</span>\n\t\t<svg role=\"img\" alt=\"\" xmlns=\"http://www.w3.org/2000/svg\" width=\"16\" height=\"16\" viewBox=\"0 0 16 16\">\n\t\t\t<path fill=\"currentColor\" d=\"M9.41,8l5.29-5.29a1,1,0,0,0-1.41-1.41L8,6.59,2.71,1.29A1,1,0,0,0,1.29,2.71L6.59,8,1.29,13.29a1,1,0,1,0,1.41,1.41L8,9.41l5.29,5.29a1,1,0,0,0,1.41-1.41Z\"/>\n\t\t</svg>\n\t</button>\n</div>",
      "rvt-alert:warning": "<div class=\"rvt-alert rvt-alert--warning rvt-m-bottom-md\" role=\"alertdialog\" aria-labelledby=\"warning-alert-title\">\n\t<h1 class=\"rvt-alert__title\" id=\"warning-alert-title\">$1</h1>\n\t<p class=\"rvt-alert__message\">$2</p>\n\t<button class=\"rvt-alert__dismiss\">\n\t\t<span class=\"v-hide\">Dismiss this alert</span>\n\t\t<svg role=\"img\" alt=\"\" xmlns=\"http://www.w3.org/2000/svg\" width=\"16\" height=\"16\" viewBox=\"0 0 16 16\">\n\t\t\t<path fill=\"currentColor\" d=\"M9.41,8l5.29-5.29a1,1,0,0,0-1.41-1.41L8,6.59,2.71,1.29A1,1,0,0,0,1.29,2.71L6.59,8,1.29,13.29a1,1,0,1,0,1.41,1.41L8,9.41l5.29,5.29a1,1,0,0,0,1.41-1.41Z\"/>\n\t\t</svg>\n\t</button>\n</div>",
      "rvt-alert:error": "<div class=\"rvt-alert rvt-alert--error\" role=\"alert\" aria-labelledby=\"error-alert-title\">\n\t<h1 class=\"rvt-alert__title\" id=\"error-alert-title\">$1</h1>\n\t<p class=\"rvt-alert__message\">$2</p>\n</div>",
      "rvt-alert:inline": "<div class=\"rvt-inline-alert rvt-inline-alert--standalone rvt-inline-alert--is-invalid\">\n\t<span class=\"rvt-inline-alert__icon\">\n\t\t<svg role=\"img\" alt=\"\" xmlns=\"http://www.w3.org/2000/svg\" width=\"16\" height=\"16\" viewBox=\"0 0 16 16\">\n\t\t\t<g fill=\"currentColor\">\n\t\t\t\t<path d=\"M8,0a8,8,0,1,0,8,8A8,8,0,0,0,8,0ZM8,14a6,6,0,1,1,6-6A6,6,0,0,1,8,14Z\" />\n\t\t\t\t\t<path d=\"M10.83,5.17a1,1,0,0,0-1.41,0L8,6.59,6.59,5.17A1,1,0,0,0,5.17,6.59L6.59,8,5.17,9.41a1,1,0,1,0,1.41,1.41L8,9.41l1.41,1.41a1,1,0,0,0,1.41-1.41L9.41,8l1.41-1.41A1,1,0,0,0,10.83,5.17Z\"/>\n\t\t\t</g>\n\t\t</svg>\n\t</span>\n\t<span class=\"rvt-inline-alert__message\" role=\"alert\" id=\"radio-list-message\">\n\t\t$1\n\t</span>\n</div>",
      "rvt-container": "<div class=\"rvt-container\">\n\t<div class=\"rvt-grid\">\n\t\t<div class=\"rvt-grid__item\">\n\t\t\t$1\n\t\t</div>\n\t</div>\n</div>",
      "rvt-container:freshman": "<div class=\"rvt-container rvt-container--freshman\">\n\t<div class=\"rvt-grid\">\n\t\t<div class=\"rvt-grid__item\">\n\t\t\t$1\n\t\t</div>\n\t</div>\n</div>",
      "rvt-container:sophomore": "<div class=\"rvt-container rvt-container--sophomore\">\n\t<div class=\"rvt-grid\">\n\t\t<div class=\"rvt-grid__item\">\n\t\t\t$1\n\t\t</div>\n\t</div>\n</div>",
      "rvt-container:junior": "<div class=\"rvt-container rvt-container--junior\">\n\t<div class=\"rvt-grid\">\n\t\t<div class=\"rvt-grid__item\">\n\t\t\t$1\n\t\t</div>\n\t</div>\n</div>",
      "rvt-container:senior": "<div class=\"rvt-container rvt-container--senior\">\n\t<div class=\"rvt-grid\">\n\t\t<div class=\"rvt-grid__item\">\n\t\t\t$1\n\t\t</div>\n\t</div>\n</div>",
      "rvt-grid-item": "<div class=\"rvt-grid__item\">\n\t$1\n</div>",
      "rvt-panel": "<div class=\"rvt-panel\">\n\t$1\n</div>",
      "rvt-panel:light": "<div class=\"rvt-panel rvt-panel--light\">\n\t$1\n</div>",
      "rvt-modal": "<div class=\"rvt-modal\"\n\tid=\"${1:modal-example-basic}\"\n\trole=\"dialog\"\n\taria-labelledby=\"${2:modal-example-title}\"\n\taria-hidden=\"true\"\n\ttabindex=-1>\n\t<div class=\"rvt-modal__inner\">\n\t\t<header class=\"rvt-modal__header\">\n\t\t\t<h1 class=\"rvt-modal__title\" id=\"$3\">${4:Modal Title}</h1>\n\t\t</header>\n\t\t<div class=\"rvt-modal__body\">\n\t\t\t<p>$5</p>\n\t\t</div>\n\t\t<div class=\"rvt-modal__controls\">\n\t\t\t<button class=\"rvt-button\">${6:OK}</button>\n\t\t\t<button class=\"rvt-button rvt-button--secondary\" data-modal-close=\"close\">${7:Cancel}</button>\n\t\t</div>\n\t\t<button class=\"rvt-button rvt-modal__close\" data-modal-close=\"close\">\n\t\t\t<span class=\"rvt-sr-only\">Close</span>\n\t\t\t<svg role=\"img\" alt=\"\" xmlns=\"http://www.w3.org/2000/svg\" width=\"16\" height=\"16\" viewBox=\"0 0 16 16\">\n\t\t\t\t<path fill=\"currentColor\" d=\"M9.41,8l5.29-5.29a1,1,0,0,0-1.41-1.41L8,6.59,2.71,1.29A1,1,0,0,0,1.29,2.71L6.59,8,1.29,13.29a1,1,0,1,0,1.41,1.41L8,9.41l5.29,5.29a1,1,0,0,0,1.41-1.41Z\"/>\n\t\t\t</svg>\n\t\t</button>\n\t</div>\n</div>",
      "rvt-list:plain": "<ul class=\"rvt-plain-list\">\n\t<li>$1</li>\n</ul>",
      "rvt-list:inline": "<ul class=\"rvt-inline-list\">\n\t<li>$1</li>\n</ul>",
      "rvt-pagination": "<nav role=\"navigation\" aria-label=\"${1:Pagination purpose label}\">\n\t<ul class=\"rvt-pagination\">\n\t\t<li class=\"rvt-pagination__item\">\n\t\t\t<a href=\"#\" aria-label=\"Previous set of pages\">Previous</a>\n\t\t</li>\n\t\t<li class=\"rvt-pagination__item\">\n\t\t\t<a href=\"#\" aria-label=\"${2:Page P-1}\">${3:P-1}</a>\n\t\t</li>\n\t\t<li class=\"rvt-pagination__item is-active\" aria-current=\"true\">\n\t\t\t<a href=\"#\" aria-label=\"${4:Page P}, current page\">${5:P}</a>\n\t\t</li>\n\t\t<li class=\"rvt-pagination__item\">\n\t\t\t<a href=\"#\" aria-label=\"${6:Page P+1}\">${7:P+1}</a>\n\t\t</li>\n\t\t<li class=\"rvt-pagination__item\">\n\t\t\t<a href=\"#\" aria-label=\"Next set of pages\">Next</a>\n\t\t</li>\n\t</ul>\n</nav>",
      "rvt-pagination:right": "<nav role=\"navigation\" aria-label=\"${1:Pagination purpose label}\">\n\t<ul class=\"rvt-pagination rvt-pagination--right\">\n\t\t<li class=\"rvt-pagination__item\">\n\t\t\t<a href=\"#\" aria-label=\"Previous set of pages\">Previous</a>\n\t\t</li>\n\t\t<li class=\"rvt-pagination__item\">\n\t\t\t<a href=\"#\" aria-label=\"${2:Page P-1}\">${3:P-1}</a>\n\t\t</li>\n\t\t<li class=\"rvt-pagination__item is-active\" aria-current=\"true\">\n\t\t\t<a href=\"#\" aria-label=\"${4:Page P}, current page\">${5:P}</a>\n\t\t</li>\n\t\t<li class=\"rvt-pagination__item\">\n\t\t\t<a href=\"#\" aria-label=\"${6:Page P+1}\">${7:P+1}</a>\n\t\t</li>\n\t\t<li class=\"rvt-pagination__item\">\n\t\t\t<a href=\"#\" aria-label=\"Next set of pages\">Next</a>\n\t\t</li>\n\t</ul>\n</nav>",
      "rvt-pagination:small": "<nav role=\"navigation\" aria-label=\"${1:Pagination purpose label}\">\n\t<ul class=\"rvt-pagination rvt-pagination--small\">\n\t\t<li class=\"rvt-pagination__item\">\n\t\t\t<a href=\"#\" aria-label=\"Previous set of pages\">Previous</a>\n\t\t</li>\n\t\t<li class=\"rvt-pagination__item\">\n\t\t\t<a href=\"#\" aria-label=\"${2:Page P-1}\">${3:P-1}</a>\n\t\t</li>\n\t\t<li class=\"rvt-pagination__item is-active\" aria-current=\"true\">\n\t\t\t<a href=\"#\" aria-label=\"${4:Page P}, current page\">${5:P}</a>\n\t\t</li>\n\t\t<li class=\"rvt-pagination__item\">\n\t\t\t<a href=\"#\" aria-label=\"${6:Page P+1}\">${7:P+1}</a>\n\t\t</li>\n\t\t<li class=\"rvt-pagination__item\">\n\t\t\t<a href=\"#\" aria-label=\"Next set of pages\">Next</a>\n\t\t</li>\n\t</ul>\n</nav>",
      "rvt-pagination:small:right": "<nav role=\"navigation\" aria-label=\"${1:Pagination purpose label}\">\n\t<ul class=\"rvt-pagination rvt-pagination--right rvt-pagination--small\">\n\t\t<li class=\"rvt-pagination__item\">\n\t\t\t<a href=\"#\" aria-label=\"Previous set of pages\">Previous</a>\n\t\t</li>\n\t\t<li class=\"rvt-pagination__item\">\n\t\t\t<a href=\"#\" aria-label=\"${2:Page P-1}\">${3:P-1}</a>\n\t\t</li>\n\t\t<li class=\"rvt-pagination__item is-active\" aria-current=\"true\">\n\t\t\t<a href=\"#\" aria-label=\"${4:Page P}, current page\">${5:P}</a>\n\t\t</li>\n\t\t<li class=\"rvt-pagination__item\">\n\t\t\t<a href=\"#\" aria-label=\"${6:Page P+1}\">${7:P+1}</a>\n\t\t</li>\n\t\t<li class=\"rvt-pagination__item\">\n\t\t\t<a href=\"#\" aria-label=\"Next set of pages\">Next</a>\n\t\t</li>\n\t</ul>\n</nav>",
      "rvt-pagination:right:small": "<nav role=\"navigation\" aria-label=\"${1:Pagination purpose label}\">\n\t<ul class=\"rvt-pagination rvt-pagination--right rvt-pagination--small\">\n\t\t<li class=\"rvt-pagination__item\">\n\t\t\t<a href=\"#\" aria-label=\"Previous set of pages\">Previous</a>\n\t\t</li>\n\t\t<li class=\"rvt-pagination__item\">\n\t\t\t<a href=\"#\" aria-label=\"${2:Page P-1}\">${3:P-1}</a>\n\t\t</li>\n\t\t<li class=\"rvt-pagination__item is-active\" aria-current=\"true\">\n\t\t\t<a href=\"#\" aria-label=\"${4:Page P}, current page\">${5:P}</a>\n\t\t</li>\n\t\t<li class=\"rvt-pagination__item\">\n\t\t\t<a href=\"#\" aria-label=\"${6:Page P+1}\">${7:P+1}</a>\n\t\t</li>\n\t\t<li class=\"rvt-pagination__item\">\n\t\t\t<a href=\"#\" aria-label=\"Next set of pages\">Next</a>\n\t\t</li>\n\t</ul>\n</nav>",
      "rvt-header": "<header class=\"rvt-header\" role=\"banner\">\n\t<a class=\"rvt-skip-link\" href=\"#main-content\">Skip to content</a>\n\t<div class=\"rvt-header__trident\">\n\t\t<svg role=\"img\" class=\"rvt-header__trident-logo\" xmlns=\"http://www.w3.org/2000/svg\" viewBox=\"0 0 41 48\" aria-describedby=\"iu-logo\">\n\t\t\t<title id=\"iu-logo\">Indiana University Logo</title>\n\t\t\t<rect width=\"41\" height=\"48\" fill=\"#900\"/>\n\t\t\t<polygon points=\"24.59 12.64 24.59 14.98 26.34 14.98 26.34 27.78 22.84 27.78 22.84 10.9 24.59 10.9 24.59 8.57 16.41 8.57 16.41 10.9 18.16 10.9 18.16 27.78 14.66 27.78 14.66 14.98 16.41 14.98 16.41 12.64 8.22 12.64 8.22 14.98 9.97 14.98 9.97 30.03 12.77 33.02 18.16 33.02 18.16 36.52 16.41 36.52 16.41 39.43 24.59 39.43 24.59 36.52 22.84 36.52 22.84 33.02 28 33.02 31.01 30.03 31.01 14.98 32.78 14.98 32.78 12.64 24.59 12.64\" fill=\"#fff\"/>\n\t\t</svg>\n\t</div>\n\t<span class=\"rvt-header__title\">\n\t\t<a href=\"#0\">${1:Application Title}</a>\n\t</span>\n</header>",
      "rvt-header:identity": "<header class=\"rvt-header\" role=\"banner\">\n\t<a class=\"rvt-skip-link\" href=\"#main-content\">Skip to content</a>\n\t<div class=\"rvt-header__trident\">\n\t\t<svg role=\"img\" alt=\"\" class=\"rvt-header__trident-logo\" xmlns=\"http://www.w3.org/2000/svg\" viewBox=\"0 0 41 48\" aria-describedby=\"iu-logo\">\n\t\t\t<title id=\"iu-logo\">Indiana University Logo</title>\n\t\t\t<rect width=\"41\" height=\"48\" fill=\"#900\"/>\n\t\t\t<polygon points=\"24.59 12.64 24.59 14.98 26.34 14.98 26.34 27.78 22.84 27.78 22.84 10.9 24.59 10.9 24.59 8.57 16.41 8.57 16.41 10.9 18.16 10.9 18.16 27.78 14.66 27.78 14.66 14.98 16.41 14.98 16.41 12.64 8.22 12.64 8.22 14.98 9.97 14.98 9.97 30.03 12.77 33.02 18.16 33.02 18.16 36.52 16.41 36.52 16.41 39.43 24.59 39.43 24.59 36.52 22.84 36.52 22.84 33.02 28 33.02 31.01 30.03 31.01 14.98 32.78 14.98 32.78 12.64 24.59 12.64\" fill=\"#fff\"/>\n\t\t</svg>\n\t</div>\n\t<span class=\"rvt-header__title\">\n\t\t<a href=\"#0\">${1:Application Title}</a>\n\t</span>\n\t<div class=\"rvt-header__controls\">\n\t\t<div class=\"rvt-header-id\">\n\t\t\t<div href=\"#0\" class=\"rvt-header-id__profile\">\n\t\t\t\t<span class=\"rvt-header-id__avatar\" aria-hidden=\"true\">${2:Avatar or initials}</span>\n\t\t\t\t<span class=\"rvt-header-id__user\">${3:username}</span>\n\t\t\t</div>\n\t\t\t<a href=\"#0\" class=\"rvt-header-id__log-out\">\n\t\t\t\tLog out\n\t\t\t</a>\n\t\t</div>\n\t\t<button class=\"rvt-drawer-button\" aria-haspopup=\"true\" aria-expanded=\"false\" data-drawer-toggle=\"mobile-drawer\">\n\t\t\t<span class=\"sr-only\">Toggle menu</span>\n\t\t\t<svg role=\"img\" alt=\"\" class=\"rvt-drawer-button-open\" xmlns=\"http://www.w3.org/2000/svg\" viewBox=\"0 0 16 16\">\n\t\t\t\t<g fill=\"currentColor\">\n\t\t\t\t\t<path d=\"M15,3H1A1,1,0,0,1,1,1H15a1,1,0,0,1,0,2Z\"/>\n\t\t\t\t\t<path d=\"M15,9H1A1,1,0,0,1,1,7H15a1,1,0,0,1,0,2Z\"/>\n\t\t\t\t\t<path d=\"M15,15H1a1,1,0,0,1,0-2H15a1,1,0,0,1,0,2Z\"/>\n\t\t\t\t</g>\n\t\t\t</svg>\n\t\t\t<svg role=\"img\" alt=\"\" class=\"rvt-drawer-button-close\" xmlns=\"http://www.w3.org/2000/svg\" viewBox=\"0 0 16 16\">\n\t\t\t\t<path fill=\"currentColor\" d=\"M9.41,8l5.29-5.29a1,1,0,0,0-1.41-1.41L8,6.59,2.71,1.29A1,1,0,0,0,1.29,2.71L6.59,8,1.29,13.29a1,1,0,1,0,1.41,1.41L8,9.41l5.29,5.29a1,1,0,0,0,1.41-1.41Z\"/>\n\t\t\t</svg>\n\t\t</button>\n\t</div>\n\t<div class=\"rvt-drawer\" aria-hidden=\"true\" id=\"mobile-drawer\">\n\t\t<div class=\"rvt-header-id rvt-header-id--drawer\">\n\t\t\t<div class=\"rvt-header-id__profile rvt-header-id__profile--drawer p-all-sm\">\n\t\t\t\t<span class=\"rvt-header-id__avatar\" aria-hidden=\"true\">${4:Avatar or initials}</span>\n\t\t\t\t<span class=\"rvt-header-id__user\">${5:username}</span>\n\t\t\t\t<a href=\"#0\" class=\"rvt-header-id__log-out\">\n\t\t\t\t\tLog out\n\t\t\t\t</a>\n\t\t\t</div>\n\t\t</div>\n\t\t<button class=\"rvt-drawer__bottom-close\">Close nav</button>\n\t</div>\n</header>",
      "rvt-header:nav": "",
      "rvt-footer": "<footer class=\"rvt-footer\" role=\"contentinfo\">\n\t<div class=\"rvt-footer__copyright-lockup\">\n\t\t<div class=rvt-footer__trident>\n\t\t\t<svg role=\"img\" aria-labelledby=\"footer-trident\" xmlns=\"http://www.w3.org/2000/svg\" width=\"20\" height=\"25\" viewBox=\"0 0 20 25\">\n\t\t\t\t<title id=\"footer-trident\">IU Trident Logo</title>\n\t\t\t\t<polygon points=\"13.33 3.32 13.33 5.21 14.76 5.21 14.76 15.64 11.9 15.64 11.9 1.9 13.33 1.9 13.33 0 6.67 0 6.67 1.9 8.09 1.9 8.09 15.64 5.24 15.64 5.24 5.21 6.67 5.21 6.67 3.32 0 3.32 0 5.21 1.43 5.21 1.43 17.47 3.7 19.91 8.09 19.91 8.09 22.76 6.67 22.76 6.67 25.13 13.33 25.13 13.33 22.76 11.9 22.76 11.9 19.91 16.1 19.91 18.56 17.47 18.56 5.21 20 5.21 20 3.32 13.33 3.32\" fill=\"#900\"/>\n\t\t\t</svg>\n\t\t</div>\n\t\t<p><a href=\"https://www.iu.edu/copyright/index.html\">Copyright</a> &copy; 2018 The Trustees of <a href=\"https://www.iu.edu/\">Indiana University</a></p>\n\t</div>\n\t<ul class=\"rvt-footer__aux-links\">\n\t\t<li class=\"rvt-footer__aux-item\">\n\t\t\t<a href=\"$1\">Privacy Policy</a>\n\t\t</li>\n\t\t<li class=\"rvt-footer__aux-item\">\n\t\t\t<a href=\"https://accessibility.iu.edu/\">Accessibility help</a>\n\t\t</li>\n\t</ul>\n</footer>",
      "rvt-tabs": "<div class=\"rvt-tabs\">\n\t<div class=\"rvt-tabs__tablist\" role=\"tablist\" aria-label=\"${1:Tabs label}\">\n\t\t<button class=\"rvt-tabs__tab\" role=\"tab\" aria-selected=\"true\" aria-controls=\"tab-1\" id=\"t-one\">\n\t\t\t${2:Tab one}\n\t\t</button>\n\t\t<button class=\"rvt-tabs__tab\" role=\"tab\" aria-selected=\"false\" aria-controls=\"tab-2\" id=\"t-two\" tabindex=\"-1\">\n\t\t\t${3:Tab two}\n\t\t</button>\n\t\t<button class=\"rvt-tabs__tab\" role=\"tab\" aria-selected=\"false\" aria-controls=\"tab-3\" id=\"t-three\" tabindex=\"-1\">\n\t\t\t${4:Tab three}\n\t\t</button>\n\t</div>\n\t<div class=\"rvt-tabs__panel\" tabindex=\"0\" role=\"tabpanel\" id=\"tab-1\" aria-labelledby=\"t-one\">\n\t\t<span class=\"rvt-ts-23 rvt-text-bold\">${5:Panel 1}</span>\n\t\t$6\n\t</div>\n\t<div class=\"rvt-tabs__panel\" tabindex=\"0\" role=\"tabpanel\" id=\"tab-2\" aria-labelledby=\"t-two\" hidden=\"\">\n\t\t<span class=\"rvt-ts-23 rvt-text-bold\">${7:Panel 2}</span>\n\t\t$8\n\t</div>\n\t$9\n</div>",
      "rvt-tabs:fitted": "<div class=\"rvt-tabs rvt-tabs--fitted\">\n\t<div class=\"rvt-tabs__tablist\" role=\"tablist\" aria-label=\"${1:Tabs label}\">\n\t\t<button class=\"rvt-tabs__tab\" role=\"tab\" aria-selected=\"true\" aria-controls=\"tab-1\" id=\"t-one\">\n\t\t\t${2:Tab one}\n\t\t</button>\n\t\t<button class=\"rvt-tabs__tab\" role=\"tab\" aria-selected=\"false\" aria-controls=\"tab-2\" id=\"t-two\" tabindex=\"-1\">\n\t\t\t${3:Tab two}\n\t\t</button>\n\t\t<button class=\"rvt-tabs__tab\" role=\"tab\" aria-selected=\"false\" aria-controls=\"tab-3\" id=\"t-three\" tabindex=\"-1\">\n\t\t\t${4:Tab three}\n\t\t</button>\n\t</div>\n\t<div class=\"rvt-tabs__panel\" tabindex=\"0\" role=\"tabpanel\" id=\"tab-1\" aria-labelledby=\"t-one\">\n\t\t<span class=\"rvt-ts-23 rvt-text-bold\">${5:Panel 1}</span>\n\t\t$6\n\t</div>\n\t<div class=\"rvt-tabs__panel\" tabindex=\"0\" role=\"tabpanel\" id=\"tab-2\" aria-labelledby=\"t-two\" hidden=\"\">\n\t\t<span class=\"rvt-ts-23 rvt-text-bold\">${7:Panel 2}</span>\n\t\t$8\n\t</div>\n\t$9\n</div>",
      "rvt-tabs:vertical": "<div class=\"rvt-tabs rvt-tabs--vertical\">\n\t<div class=\"rvt-tabs__tablist\" role=\"tablist\" aria-orientation=\"vertical\"  aria-label=\"${1:Tabs label}\">\n\t\t<button class=\"rvt-tabs__tab\" role=\"tab\" aria-selected=\"true\" aria-controls=\"tab-1\" id=\"t-one\">\n\t\t\t${2:Tab one}\n\t\t</button>\n\t\t<button class=\"rvt-tabs__tab\" role=\"tab\" aria-selected=\"false\" aria-controls=\"tab-2\" id=\"t-two\" tabindex=\"-1\">\n\t\t\t${3:Tab two}\n\t\t</button>\n\t\t<button class=\"rvt-tabs__tab\" role=\"tab\" aria-selected=\"false\" aria-controls=\"tab-3\" id=\"t-three\" tabindex=\"-1\">\n\t\t\t${4:Tab three}\n\t\t</button>\n\t</div>\n\t<div class=\"rvt-tabs__panel\" tabindex=\"0\" role=\"tabpanel\" id=\"tab-1\" aria-labelledby=\"t-one\">\n\t\t<span class=\"rvt-ts-23 rvt-text-bold\">${5:Panel 1}</span>\n\t\t$6\n\t</div>\n\t<div class=\"rvt-tabs__panel\" tabindex=\"0\" role=\"tabpanel\" id=\"tab-2\" aria-labelledby=\"t-two\" hidden=\"\">\n\t\t<span class=\"rvt-ts-23 rvt-text-bold\">${7:Panel 2}</span>\n\t\t$8\n\t</div>\n\t$9\n</div>",
      "rvt-tab": "<div class=\"rvt-tabs__panel\" tabindex=\"0\" role=\"tabpanel\" id=\"tab-${1:#}\" aria-labelledby=\"t-${2:number}\" hidden=\"\">\n\t<span class=\"rvt-ts-23 rvt-text-bold\">${3:Panel title}</span>\n\t$4\n</div>",
      "rvt-dropdown": "<div class=\"rvt-dropdown\">\n\t<button class=\"rvt-button\" data-dropdown-toggle=\"${1:dropdown-id}\" aria-haspopup=\"true\" aria-expanded=\"false\">\n\t\t<span>${2:Dropdown label}</span>\n\t\t<svg role=\"img\" alt=\"\" class=\"rvt-m-left-xs\" xmlns=\"http://www.w3.org/2000/svg\" width=\"16\" height=\"16\" viewBox=\"0 0 16 16\">\n\t\t\t<path fill=\"currentColor\" d=\"M8,12.46a2,2,0,0,1-1.52-.7L1.24,5.65a1,1,0,1,1,1.52-1.3L8,10.46l5.24-6.11a1,1,0,0,1,1.52,1.3L9.52,11.76A2,2,0,0,1,8,12.46Z\"/>\n\t\t</svg>\n\t</button>\n\t<div class=\"rvt-dropdown__menu\" id=\"${3:dropdown-id}\" aria-hidden=\"true\" role=\"menu\">\n\t\t<a href=\"$4\" aria-current=\"page\">${5:Dropdown item}</a>\n\t\t<a href=\"$6\">${7:Dropdown item}</a>\n\t\t<div role=\"group\" aria-label=\"Related\">\n\t\t\t<a href=\"$8\">${9:Dropdown item}</a>\n\t\t</div>\n\t</div>\n</div>",
      "rvt-dropdown-item-group": "<div role=\"group\" aria-label=\"Related\">\n\t<a href=\"$1\">${2:Dropdown item}</a>\n</div>",
      "rvt-breadcrumbs": "<nav role=\"navigation\" aria-label=\"${1:Breadcrumbs label}\">\n\t<ol class=\"rvt-breadcrumbs\">\n\t\t<li><a href=\"$2\">${3:Section title}</a></li>\n\t\t<li aria-label=\"Current page\">${4:Page title}</li>\n\t</ol>\n</nav>",
      "rvt-breadcrumbs:callout": "<nav role=\"navigation\" aria-label=\"${1:Breadcrumbs label}\">\n\t<ol class=\"rvt-breadcrumbs rvt-breadcrumbs--call-out\">\n\t\t<li><a href=\"$2\">${3:Section title}</a></li>\n\t\t<li aria-label=\"Current page\">${4:Page title}</li>\n\t</ol>\n</nav>",
      "rvt-table": "<table>\n\t<caption class=\"sr-only\">${1:Table summary}</caption>\n\t<thead>\n\t\t<tr>\n\t\t\t<th scope=\"col\">$2</th>\n\t\t\t<th scope=\"col\">$3</th>\n\t\t</tr>\n\t</thead>\n\t<tbody>\n\t\t<tr>\n\t\t\t<th scope=\"row\">$4</th>\n\t\t\t<td>$5</td>\n\t\t</tr>\n\t\t$6\n\t</tbody>\n</table>",
      "rvt-table:striped": "<table class=\"rvt-table-stripes\">\n\t<caption class=\"sr-only\">${1:Table summary}</caption>\n\t<thead>\n\t\t<tr>\n\t\t\t<th scope=\"col\">$2</th>\n\t\t\t<th scope=\"col\">$3</th>\n\t\t</tr>\n\t</thead>\n\t<tbody>\n\t\t<tr>\n\t\t\t<th scope=\"row\">$4</th>\n\t\t\t<td>$5</td>\n\t\t</tr>\n\t\t$6\n\t</tbody>\n</table>",
      "rvt-table:plain": "<table class=\"rvt-table-plain\">\n\t<caption class=\"sr-only\">${1:Table summary}</caption>\n\t<thead>\n\t\t<tr>\n\t\t\t<th scope=\"col\">$2</th>\n\t\t\t<th scope=\"col\">$3</th>\n\t\t</tr>\n\t</thead>\n\t<tbody>\n\t\t<tr>\n\t\t\t<th scope=\"row\">$4</th>\n\t\t\t<td>$5</td>\n\t\t</tr>\n\t\t$6\n\t</tbody>\n</table>"

    },
    "abbreviations": {
      "rvt-badge": "<span class=\"rvt-badge\">|</span>",
      "rvt-badge:action": "<span class=\"rvt-badge rvt-badge--action\">|</span>",
      "rvt-badge:success": "<span class=\"rvt-badge rvt-badge--success\">|</span>",
      "rvt-badge:warning": "<span class=\"rvt-badge rvt-badge--warning\">|</span>",
      "rvt-badge:error": "<span class=\"rvt-badge rvt-badge--error\">|</span>",
      "rvt-badge:secondary": "<span class=\"rvt-badge rvt-badge--secondary\">|</span>",
      "rvt-badge:secondary:action": "<span class=\"rvt-badge rvt-badge--action-secondary\">|</span>",
      "rvt-badge:secondary:success": "<span class=\"rvt-badge rvt-badge--success-secondary\">|</span>",
      "rvt-badge:secondary:warning": "<span class=\"rvt-badge rvt-badge--warning-secondary\">|</span>",
      "rvt-badge:secondary:error": "<span class=\"rvt-badge rvt-badge--error-secondary\">|</span>",
      "rvt-button": "<button class=\"rvt-button\">|</button>",
      "rvt-button:success": "<button class=\"rvt-button rvt-button--success\">|</button>",
      "rvt-button:danger": "<button class=\"rvt-button rvt-button--danger\">|</button>",
      "rvt-button:plain": "<button class=\"rvt-button rvt-button--plain\">|</button>",
      "rvt-button:secondary": "<button class=\"rvt-button rvt-button--secondary\">|</button>",
      "rvt-button:secondary:success": "<button class=\"rvt-button rvt-button--success-secondary\">|</button>",
      "rvt-button:secondary:danger": "<button class=\"rvt-button rvt-button--danger-secondary\">|</button>",
      "rvt-button:small": "<button class=\"rvt-button rvt-button--small\">|</button>",
      "rvt-button:small:success": "<button class=\"rvt-button rvt-button--small rvt-button--success\">|</button>",
      "rvt-button:small:danger": "<button class=\"rvt-button rvt-button--small rvt-button--danger\">|</button>",
      "rvt-button:small:plain": "<button class=\"rvt-button rvt-button--small rvt-button--plain\">|</button>",
      "rvt-button:secondary:small": "<button class=\"rvt-button rvt-button--small rvt-button--secondary\">|</button>",
      "rvt-button:secondary:small:success": "<button class=\"rvt-button rvt-button--small rvt-button--success-secondary\">|</button>",
      "rvt-button:secondary:small:danger": "<button class=\"rvt-button rvt-button--small rvt-button--danger-secondary\">|</button>",
      "rvt-button:small:secondary": "<button class=\"rvt-button rvt-button--small rvt-button--secondary\">|</button>",
      "rvt-button:small:secondary:success": "<button class=\"rvt-button rvt-button--small rvt-button--success-secondary\">|</button>",
      "rvt-button:small:secondary:danger": "<button class=\"rvt-button rvt-button--small rvt-button--danger-secondary\">|</button>",
      "rvt-button:modal": "<button class=\"rvt-button\" data-modal-trigger=\"$1\">$2</button>",
      "rvt-h1": "<h1 class=\"rvt-ts-32\">|</h1>",
      "rvt-h2": "<h2 class=\"rvt-ts-26\">|</h2>",
      "rvt-h3": "<h3 class=\"rvt-ts-18\">|</h3>",
      "rvt-p": "<p class=\"rvt-ts-base\">|</p>"
    }
  }
}
